.bumpversion.cfg
CONTRIBUTING.md
LICENSE
MANIFEST.in
Makefile
README.md
pyproject.toml
requirements.txt
setup.py
Splotify.egg-info/PKG-INFO
Splotify.egg-info/SOURCES.txt
Splotify.egg-info/dependency_links.txt
Splotify.egg-info/requires.txt
Splotify.egg-info/top_level.txt
examples/radiohead_box_plot.png
examples/radiohead_pie_chart.png
examples/radiohead_scatter_plot.png
splotify/__init__.py
splotify/data.py
splotify/helpers.py
splotify/spotifyapi.py
splotify/plots/__init__.py
splotify/plots/audiofeatures.py
splotify/plots/category.py
splotify/plots/popularity.py
splotify/tests/__init__.py
splotify/tests/conftest.py
splotify/tests/test_audiofeatures.py
splotify/tests/test_category.py
splotify/tests/test_data.py
splotify/tests/test_helpers.py
splotify/tests/test_integration.py
splotify/tests/test_popularity.py
splotify/tests/cassettes/splotify.tests.test_audiofeatures/test_box_plot.yaml
splotify/tests/cassettes/splotify.tests.test_audiofeatures/test_histogram.yaml
splotify/tests/cassettes/splotify.tests.test_audiofeatures/test_scatter_plot_2d.yaml
splotify/tests/cassettes/splotify.tests.test_audiofeatures/test_scatter_plot_2d_average.yaml
splotify/tests/cassettes/splotify.tests.test_audiofeatures/test_scatter_plot_3d.yaml
splotify/tests/cassettes/splotify.tests.test_audiofeatures/test_scatter_plot_3d_average.yaml
splotify/tests/cassettes/splotify.tests.test_audiofeatures/test_select_features.yaml
splotify/tests/cassettes/splotify.tests.test_data/test_add_albums.yaml
splotify/tests/cassettes/splotify.tests.test_data/test_add_playlists.yaml
splotify/tests/cassettes/splotify.tests.test_data/test_add_tracks.yaml
splotify/tests/cassettes/splotify.tests.test_helpers/test_my_id.yaml
splotify/tests/cassettes/splotify.tests.test_helpers/test_search_id.yaml
splotify/tests/cassettes/splotify.tests.test_integration/test_integration.yaml
splotify/tests/cassettes/splotify.tests.test_popularity/test_album_bar_chart.yaml
splotify/tests/cassettes/splotify.tests.test_popularity/test_track_bar_chart.yaml
splotify/tests/expected_plot_outputs/test_album_bar_chart.png
splotify/tests/expected_plot_outputs/test_bar_chart.png
